beancount-stubs/loader.pyi
beancount-stubs/core/account.pyi
beancount-stubs/core/account_types.pyi
beancount-stubs/core/amount.pyi
beancount-stubs/core/compare.pyi
beancount-stubs/core/convert.pyi
beancount-stubs/core/data.pyi
beancount-stubs/core/display_context.pyi
beancount-stubs/core/distribution.pyi
beancount-stubs/core/flags.pyi
beancount-stubs/core/getters.pyi
beancount-stubs/core/interpolate.pyi
beancount-stubs/core/inventory.pyi
beancount-stubs/core/number.pyi
beancount-stubs/core/position.pyi
beancount-stubs/core/prices.pyi
beancount-stubs/core/realization.pyi
beancount-stubs/ingest/cache.pyi
beancount-stubs/ingest/importer.pyi
beancount-stubs/ingest/regression_pytest.pyi
beancount-stubs/query/numberify.pyi
beancount-stubs/query/query.pyi
beancount-stubs/query/query_compile.pyi
beancount-stubs/query/query_execute.pyi
beancount_stubs-0.1.5.dist-info/LICENSE
beancount_stubs-0.1.5.dist-info/METADATA
beancount_stubs-0.1.5.dist-info/WHEEL
beancount_stubs-0.1.5.dist-info/top_level.txt
beancount_stubs-0.1.5.dist-info/RECORD
