Metadata-Version: 2.1
Name: beancount-stubs
Version: 0.1.5
Summary: Stub files for the beancount package
Author-email: Joshua Gilman <joshuagilman@gmail.com>
License: Copyright 2022 Joshua Gilman
Project-URL: Repository, https://github.com/jmgilman/beancount-stubs
Keywords: beancount,stubs,mypy,types
Requires-Python: >=3.8.18
License-File: LICENSE
Requires-Dist: beancount <3,>=2.3.6
